<languages><language><languageT id="0">Incontro</languageT><languageT id="1">Formazione</languageT><languageT id="2">Torneo</languageT><languageT id="3">Stagione</languageT><languageT id="4">Sei sicuro di voler uscire?</languageT><languageT id="5">Creato da Igor Ayello Borges</languageT><languageT id="6">linguaggio</languageT><languageT id="7">Inglese</languageT><languageT id="8">portoghese</languageT><languageT id="9">Difficile</languageT><languageT id="10">Facile</languageT><languageT id="11">Normale</languageT><languageT id="12">Difficile</languageT><languageT id="13">Controllo</languageT><languageT id="14">Tastiera</languageT><languageT id="15">Telecomando da gioco</languageT><languageT id="16">Telecomando da gioco</languageT><languageT id="17">Ridefinisci i pulsanti</languageT><languageT id="18">Menu principale</languageT><languageT id="19">Opzioni</languageT><languageT id="20">Caricare</languageT><languageT id="21">modificare</languageT><languageT id="22">Titoli di coda</languageT><languageT id="23">Smettere</languageT><languageT id="24">Argentina</languageT><languageT id="25">Australia</languageT><languageT id="26">Belgio</languageT><languageT id="27">Brasile</languageT><languageT id="28">Bulgaria</languageT><languageT id="29">Camerun</languageT><languageT id="30">Canada</languageT><languageT id="31">Chile</languageT><languageT id="32">Cina</languageT><languageT id="33">Cuba</languageT><languageT id="34">Cecoslovacchia</languageT><languageT id="35">Germania dell'est</languageT><languageT id="36">Egitto</languageT><languageT id="37">Finlandia</languageT><languageT id="38">Francia</languageT><languageT id="39">Grecia</languageT><languageT id="40">Italia</languageT><languageT id="41">Giappone</languageT><languageT id="42">Libia</languageT><languageT id="43">Messico</languageT><languageT id="44">Olanda</languageT><languageT id="45">Polonia</languageT><languageT id="46">Romania</languageT><languageT id="47">Corea del Sud</languageT><languageT id="48">Unione Sovietica</languageT><languageT id="49">Spagna</languageT><languageT id="50">Svezia</languageT><languageT id="51">Tunisia</languageT><languageT id="52">stati Uniti</languageT><languageT id="53">Venezuela</languageT><languageT id="54">Germania dell'Ovest</languageT><languageT id="55">Jugoslavia</languageT><languageT id="56">Kit</languageT><languageT id="57">Giocare</languageT><languageT id="58">Pausa</languageT><languageT id="59">Continua</languageT><languageT id="60">Caricamento in corso</languageT><languageT id="61">Fine del gioco</languageT><languageT id="62">Indietro</languageT><languageT id="63">Definisci gli input</languageT><languageT id="64">Su</languageT><languageT id="65">Giù</languageT><languageT id="66">Sinistra</languageT><languageT id="67">Destra</languageT><languageT id="68">Azione</languageT><languageT id="69">Pausa</languageT><languageT id="70">Servire</languageT><languageT id="71">Ricevere</languageT><languageT id="72">Coppa del Sud America</languageT><languageT id="73">Coppa America</languageT><languageT id="74">Coppa d'Africa</languageT><languageT id="75">Coppa d'Asia</languageT><languageT id="76">Coppa Europa</languageT><languageT id="77">Qualificazioni per la Coppa Europa</languageT><languageT id="78">Qualificazione per la medaglia d'oro</languageT><languageT id="79">Campionato Internazionale</languageT><languageT id="80">Torneo internazionale</languageT><languageT id="81">Medaglia d'oro</languageT><languageT id="82">Le prime 2 squadre si qualificano per il campionato internazionale.</languageT><languageT id="83">Le migliori 8 squadre si qualificano per il campionato internazionale.</languageT><languageT id="84">Le migliori 8 squadre si qualificano per il campionato internazionale.</languageT><languageT id="85">La squadra più qualificata va al Torneo Internazionale.</languageT><languageT id="86">Le prime 3 squadre si qualificano per il torneo internazionale.</languageT><languageT id="87">Le prime 3 squadre si qualificano per la medaglia d'oro.</languageT><languageT id="88">La squadra più qualificata va alla medaglia d'oro.</languageT><languageT id="89">Le prime 2 squadre di ogni gruppo si qualificano per la medaglia d'oro.</languageT><languageT id="90">Le prime 3 squadre di ogni girone si qualificano per la Coppa Europa.</languageT><languageT id="91">La seconda squadra più qualificata va alle qualificazioni per la medaglia d'oro.</languageT><languageT id="92">Le prime 4 squadre si qualificano per la medaglia d'oro.</languageT><languageT id="93">Sei sicuro di voler uscire? Tutte le modifiche non salvate andranno perse.</languageT><languageT id="94">Turno 1</languageT><languageT id="95">Turno 2</languageT><languageT id="96">Turno 3</languageT><languageT id="97">Selezione della squadra</languageT><languageT id="98">Simulare</languageT><languageT id="99">Sei sicuro di voler simulare questo gioco?</languageT><languageT id="100">Classifica finale</languageT><languageT id="101">Indietro al menù principale</languageT><languageT id="102">Vai alla cerimonia</languageT><languageT id="103">Gruppo</languageT><languageT id="104">Questo round non è ancora iniziato.</languageT><languageT id="105">Salva</languageT><languageT id="106">Gioco salvato con successo</languageT><languageT id="107">Impossibile salvare il gioco</languageT><languageT id="108">Vuoto</languageT><languageT id="109">Sei sicuro di voler eliminare questo gioco salvato?</languageT><languageT id="110">Il prossimo</languageT><languageT id="111">Sei qualificato per la Coppa Europa</languageT><languageT id="112">Sei qualificato per il campionato internazionale</languageT><languageT id="113">Spiacente, non sei qualificato per il prossimo torneo!</languageT><languageT id="114">Sei qualificato per il torneo internazionale</languageT><languageT id="115">Sei qualificato per la medaglia d'oro</languageT><languageT id="116">Questa è la fine della medaglia d'oro</languageT><languageT id="117">Obbiettivo</languageT><languageT id="118">Storico</languageT><languageT id="119">Prova a vincere la medaglia d'oro</languageT><languageT id="120">Sei qualificato per le qualificazioni per la medaglia d'oro</languageT><languageT id="121">Sempre</languageT><languageT id="122">Tutti i tornei</languageT><languageT id="123">Contro</languageT><languageT id="124">Contro dettagliato</languageT><languageT id="125">Anno</languageT><languageT id="126">Questa è la modalità di fine stagione.</languageT><languageT id="127">Benvenuto nel tutorial sulla pallavolo degli anni '80, in questa modalità imparerai a giocare.</languageT><languageT id="128">Hai due opzioni per servire, il servizio normale e il servizio saltato. Servizio normale. 1. Premere il pulsante direzionale destro 2. Premere il pulsante azione 3. Premere il pulsante destro, sinistro, su o giù per scegliere dove servire</languageT><languageT id="129">Salta il servizio 1. Premi il pulsante direzionale sinistro 2. Tieni premuto il pulsante di azione per aumentare la barra di potenza arancione 3. Quando la barra di potenza arancione rimane tra due barre bianche, rilascia il pulsante di azione. 4. Se la barra arancione della potenza rimane al di fuori delle due barre bianche, il giocatore servirà fuori 5. Premi il pulsante destro, sinistro, su o giù per scegliere dove servire</languageT><languageT id="130">Per bloccare 1. Premere il pulsante su o giù per spostare i bloccanti 2. Premere il pulsante di azione per saltare</languageT><languageT id="131">Per difendere 1. premere il pulsante sinistro o destro per muovere la difesa 2. è sufficiente toccare la palla</languageT><languageT id="132">Per ricevere 1. Il giocatore che riceverà ha un marcatore circolare bianco 2. Premi su, giù, sinistra o destra per muovere il giocatore 3. Devi solo toccare la palla per ricevere 4. Se tocchi la palla con le mani del giocatore sarà una buona ricezione quindi il palleggiatore ha cinque opzioni per attaccare 5. Se tocchi la palla con la testa del giocatore sarà una cattiva ricezione quindi il palleggiatore ha solo due opzioni per attaccare</languageT><languageT id="133">Per impostare il gioco 1. Premi i pulsanti su, giù, sinistra o destra per scegliere l'attaccante 2. Ogni pulsante direzionale corrisponde a un attaccante</languageT><languageT id="134">Per attaccare 1. Tieni premuto il pulsante di azione per aumentare la barra della potenza arancione 2. Quando la barra della potenza arancione rimane tra due barre bianche, rilascia il pulsante 3. Premi il pulsante destro, sinistro, su o giù per scegliere dove attaccare</languageT><languageT id="135">Hai terminato la modalità tutorial. È possibile accedere a questa modalità facendo clic sull'icona del tutorial.</languageT><languageT id="136">Errore</languageT><languageT id="137">Impossibile caricare la lingua, chiudere il gioco e ricominciare.</languageT><languageT id="138">Impossibile eliminare il file, riprova.</languageT><languageT id="139">Impossibile caricare il gioco, riprova.</languageT></language></languages>